{
  "hash": "69ed8591",
  "configHash": "52a1a99e",
  "lockfileHash": "3c251434",
  "browserHash": "8f3f2cc4",
  "optimized": {
    "react/jsx-dev-runtime": {
      "src": "../../node_modules/react/jsx-dev-runtime.js",
      "file": "react_jsx-dev-runtime.js",
      "fileHash": "156794f0",
      "needsInterop": true
    },
    "react": {
      "src": "../../node_modules/react/index.js",
      "file": "react.js",
      "fileHash": "093b6d43",
      "needsInterop": true
    },
    "react-dom/client": {
      "src": "../../node_modules/react-dom/client.js",
      "file": "react-dom_client.js",
      "fileHash": "57764071",
      "needsInterop": true
    },
    "sonner": {
      "src": "../../node_modules/sonner/dist/index.mjs",
      "file": "sonner.js",
      "fileHash": "5401d33d",
      "needsInterop": false
    },
    "@tanstack/react-query": {
      "src": "../../node_modules/@tanstack/react-query/build/modern/index.js",
      "file": "@tanstack_react-query.js",
      "fileHash": "674bd5d1",
      "needsInterop": false
    },
    "react-router-dom": {
      "src": "../../node_modules/react-router-dom/dist/index.js",
      "file": "react-router-dom.js",
      "fileHash": "04238bea",
      "needsInterop": false
    },
    "lucide-react": {
      "src": "../../node_modules/lucide-react/dist/esm/lucide-react.js",
      "file": "lucide-react.js",
      "fileHash": "ce6e2a8e",
      "needsInterop": false
    }
  },
  "chunks": {
    "chunk-7LVE3BO7": {
      "file": "chunk-7LVE3BO7.js"
    },
    "chunk-ZCND2HWC": {
      "file": "chunk-ZCND2HWC.js"
    }
  }
}